[
	{
		"__TYPE__": "SharedSliceContent",
		"variation": "default",
		"primary": {
			"heading": {
				"__TYPE__": "StructuredTextContent",
				"value": [
					{
						"type": "heading2",
						"content": {
							"text": "Government"
						}
					}
				]
			},
			"image": {
				"origin": {
					"id": "main",
					"url": "https://images.unsplash.com/photo-1589321599763-d66926c29613",
					"width": 3168,
					"height": 4752
				},
				"url": "https://images.unsplash.com/photo-1589321599763-d66926c29613",
				"width": 3168,
				"height": 4752,
				"edit": {
					"zoom": 1,
					"crop": {
						"x": 0,
						"y": 0
					},
					"background": "transparent"
				},
				"alt": "package",
				"credits": null,
				"__TYPE__": "ImageContent",
				"thumbnails": {}
			},
			"icon": {
				"__TYPE__": "FieldContent",
				"value": "cycle",
				"type": "Select"
			},
			"subheading": {
				"__TYPE__": "StructuredTextContent",
				"value": [
					{
						"type": "heading3",
						"content": {
							"text": "Height"
						}
					}
				]
			},
			"body": {
				"__TYPE__": "StructuredTextContent",
				"value": [
					{
						"type": "paragraph",
						"content": {
							"text": "Quis sunt ex duis sint do adipisicing anim non est."
						}
					}
				]
			},
			"button_text": {
				"__TYPE__": "FieldContent",
				"value": "drop",
				"type": "Text"
			},
			"button_link": {
				"key": "2b2b2068-bad9-4029-b053-99a00625eb64",
				"__TYPE__": "LinkContent",
				"value": {
					"__TYPE__": "ExternalLink",
					"url": "https://prismic.io",
					"text": "mostly"
				}
			}
		},
		"items": []
	}
]